README.md
setup.py
pieparty/__init__.py
pieparty/piemain.py
pieparty.egg-info/PKG-INFO
pieparty.egg-info/SOURCES.txt
pieparty.egg-info/dependency_links.txt
pieparty.egg-info/entry_points.txt
pieparty.egg-info/not-zip-safe
pieparty.egg-info/requires.txt
pieparty.egg-info/top_level.txt